tsm/__init__.py
tsm/tsm.py
tsm-8.0.3.dist-info/DESCRIPTION.rst
tsm-8.0.3.dist-info/METADATA
tsm-8.0.3.dist-info/RECORD
tsm-8.0.3.dist-info/WHEEL
tsm-8.0.3.dist-info/metadata.json
tsm-8.0.3.dist-info/top_level.txt
