Metadata-Version: 2.0
Name: tsm
Version: 8.0.3
Summary: Twitter Subgraph Manipulator (TSM)
Home-page: https://github.com/dfreelon/tsm/
Author: Deen Freelon
Author-email: dfreelon@gmail.com
License: UNKNOWN
Download-URL: https://github.com/dfreelon/tsm/tarball/8.0
Keywords: twitter,network analysis,data science,big data
Platform: UNKNOWN
Requires-Dist: python-louvain
Requires-Dist: networkx
